vonzy/__init__.py
vonzy/__main__.py
vonzy/actions/__init__.py
vonzy/actions/base.py
vonzy/actions/rsync.py
vonzy/actions/shell.py
vonzy/actions/ssh.py
vonzy/constants.py
vonzy/datatype.py
vonzy/errors.py
vonzy/logger.py
vonzy/schema.py
vonzy/utils.py
vonzy-0.1.1a0.dist-info/LICENSE
vonzy-0.1.1a0.dist-info/METADATA
vonzy-0.1.1a0.dist-info/WHEEL
vonzy-0.1.1a0.dist-info/entry_points.txt
vonzy-0.1.1a0.dist-info/RECORD
