Metadata-Version: 2.1
Name: vonzy
Version: 0.1.1a0
Summary: Simple task runner for automation
License: MIT
Author: Aprila Hijriyan
Author-email: hijriyan23@gmail.com
Requires-Python: >=3.8,<4.0
Classifier: License :: OSI Approved :: MIT License
Classifier: Programming Language :: Python :: 3
Classifier: Programming Language :: Python :: 3.8
Classifier: Programming Language :: Python :: 3.9
Classifier: Programming Language :: Python :: 3.10
Classifier: Programming Language :: Python :: 3.11
Requires-Dist: addict (>=2.4.0,<3.0.0)
Requires-Dist: inquirer (>=3.1.3,<4.0.0)
Requires-Dist: jinja2 (>=3.1.2,<4.0.0)
Requires-Dist: oyaml (>=1.0,<2.0)
Requires-Dist: pexpect (>=4.8.0,<5.0.0)
Requires-Dist: pydantic (>=1.10.9,<2.0.0)
Requires-Dist: typer[all] (>=0.9.0,<0.10.0)
